apicall/__init__.py
apicall/__main__.py
apicall/arguments.py
apicall/config.py
apicall/jsonrpc.py
apicall/main.py
apicall/printutils.py
apicall/restapi.py
apicall/urlutils.py
apicall/version.py
apicall-0.2.1.dist-info/licenses/LICENSE
apicall-0.2.1.dist-info/METADATA
apicall-0.2.1.dist-info/WHEEL
apicall-0.2.1.dist-info/entry_points.txt
apicall-0.2.1.dist-info/top_level.txt
apicall-0.2.1.dist-info/RECORD
