Metadata-Version: 2.4
Name: apicall
Version: 0.2.1
Summary: User-friendly RESTful API & JSON-RPC Client
Home-page: https://github.com/yuuki0xff/apicall
Author: The Python Packaging Authority
Author-email: yuuki0xff@gmail.com
Project-URL: Bug Reports, https://github.com/yuuki0xff/apicall/issues
Project-URL: Source, https://github.com/yuuki0xff/apicall
Keywords: development rest api json-rpc http client
Classifier: Development Status :: 4 - Beta
Classifier: Intended Audience :: Developers
Classifier: Environment :: Console
Classifier: Operating System :: POSIX :: Linux
Classifier: Topic :: Software Development
Classifier: License :: OSI Approved :: MIT License
Classifier: Programming Language :: Python :: 3
Classifier: Programming Language :: Python :: 3.9
Classifier: Programming Language :: Python :: 3.10
Classifier: Programming Language :: Python :: 3.11
Classifier: Programming Language :: Python :: 3.12
Classifier: Programming Language :: Python :: 3.13
License-File: LICENSE
Requires-Dist: tabulate
Requires-Dist: dataclasses-json>=0.5.0
Requires-Dist: requests
Requires-Dist: jsonrpcclient<5,>=4.0.0
Provides-Extra: dev
Requires-Dist: yapf; extra == "dev"
Requires-Dist: mypy; extra == "dev"
Requires-Dist: pytest; extra == "dev"
Requires-Dist: types-requests; extra == "dev"
Dynamic: author
Dynamic: author-email
Dynamic: classifier
Dynamic: description
Dynamic: description-content-type
Dynamic: home-page
Dynamic: keywords
Dynamic: license-file
Dynamic: project-url
Dynamic: provides-extra
Dynamic: requires-dist
Dynamic: summary
